faim_ipa/__init__.py
faim_ipa/dask_utils.py
faim_ipa/histogram.py
faim_ipa/metaseries_utils_dask.py
faim_ipa/mobie.py
faim_ipa/utils.py
faim_ipa/zarr_utils.py
faim_ipa/alignment/__init__.py
faim_ipa/alignment/alignment.py
faim_ipa/detection/__init__.py
faim_ipa/detection/blobs.py
faim_ipa/detection/spots.py
faim_ipa/detection/utils.py
faim_ipa/eicm/__init__.py
faim_ipa/eicm/estimator/__init__.py
faim_ipa/eicm/estimator/gaussian2D_fit.py
faim_ipa/eicm/estimator/gaussian_blur.py
faim_ipa/eicm/estimator/polynomial_fit.py
faim_ipa/eicm/estimator/utils.py
faim_ipa/eicm/preprocessing/__init__.py
faim_ipa/eicm/preprocessing/cellvoyager.py
faim_ipa/eicm/preprocessing/multiple_tiles.py
faim_ipa/hcs/__init__.py
faim_ipa/hcs/acquisition.py
faim_ipa/hcs/converter.py
faim_ipa/hcs/plate.py
faim_ipa/hcs/cellvoyager/__init__.py
faim_ipa/hcs/cellvoyager/acquisition.py
faim_ipa/hcs/cellvoyager/tile.py
faim_ipa/hcs/imagexpress/__init__.py
faim_ipa/hcs/imagexpress/acquisition.py
faim_ipa/io/__init__.py
faim_ipa/io/metadata.py
faim_ipa/io/metaseries.py
faim_ipa/pixi/__init__.py
faim_ipa/pixi/cache_status.py
faim_ipa/pixi/log_commit.py
faim_ipa/pixi/src_status.py
faim_ipa/stitching/__init__.py
faim_ipa/stitching/bounding_box.py
faim_ipa/stitching/dask.py
faim_ipa/stitching/stitching_utils.py
faim_ipa/stitching/tile.py
faim_ipa/visiview/__init__.py
faim_ipa/visiview/acquisition.py
faim_ipa/visiview/ome_companion_utils.py
faim_ipa-0.14.0.dist-info/METADATA
faim_ipa-0.14.0.dist-info/WHEEL
faim_ipa-0.14.0.dist-info/licenses/LICENSE
faim_ipa-0.14.0.dist-info/RECORD
