Metadata-Version: 2.4
Name: faim-ipa
Version: 0.14.0
Summary: Tools used at FMI-FAIM for Image Processing and Analysis.
Project-URL: Bug Tracker, https://github.com/fmi-faim/faim-ipa/issues
Project-URL: Documentation, https://github.com/fmi-faim/faim-ipa#README.md
Project-URL: Homepage, https://github.com/fmi-faim/faim-ipa.git
Project-URL: Source Code, https://github.com/fmi-faim/faim-ipa
Project-URL: User Support, https://github.com/fmi-faim/faim-ipa/issues
Author-email: Tim-Oliver Buchholz <tim-oliver.buchholz@fmi.ch>, Jan Eglinger <jan.eglinger@fmi.ch>
License-Expression: BSD-3-Clause
License-File: LICENSE
Classifier: Development Status :: 4 - Beta
Classifier: Programming Language :: Python
Classifier: Programming Language :: Python :: 3.10
Classifier: Programming Language :: Python :: 3.11
Classifier: Programming Language :: Python :: 3.12
Classifier: Programming Language :: Python :: 3.13
Classifier: Programming Language :: Python :: Implementation :: CPython
Classifier: Programming Language :: Python :: Implementation :: PyPy
Requires-Python: >=3.10
Requires-Dist: defusedxml
Requires-Dist: distributed
Requires-Dist: matplotlib
Requires-Dist: numpy
Requires-Dist: ome-zarr
Requires-Dist: pandas
Requires-Dist: pint
Requires-Dist: pydantic>=2
Requires-Dist: questionary
Requires-Dist: scikit-image
Requires-Dist: tqdm
Requires-Dist: zarr<3
